<?xml version="1.0" encoding="UTF-8"?>
<objects serializationModel="Studio.02.02.00">
	<object class="ParameterPreset" id="{dfc92d7c-3252-4554-b996-f9cedeecfd80}">
		<property name="name">
			<value>insanity</value>
		</property>
		<relationship name="folder">
			<destination>{6d6adf16-4adc-493d-8b0f-1dff473c03f0}</destination>
		</relationship>
		<relationship name="parameter">
			<destination>{abe6ff13-d3a5-4338-8674-3999da8e84ac}</destination>
		</relationship>
	</object>
	<object class="GameParameter" id="{abe6ff13-d3a5-4338-8674-3999da8e84ac}">
		<property name="maximum">
			<value>100</value>
		</property>
		<property name="initialValue">
			<value>0</value>
		</property>
	</object>
</objects>
